pypipackage/__init__.py
pypipackage/admin.py
pypipackage/apps.py
pypipackage/models.py
pypipackage/tests.py
pypipackage/urls.py
pypipackage/views.py
pypipackage/migrations/__init__.py
pypipackage/templates/pypipackage/home.html
alou_demo_py-0.0.1.dist-info/METADATA
alou_demo_py-0.0.1.dist-info/WHEEL
alou_demo_py-0.0.1.dist-info/top_level.txt
alou_demo_py-0.0.1.dist-info/RECORD
